{"konami_id": 16335, "name": {"en": "Etraynze the Shadow Flower Ninja", "de": "Etraynze die Schattenblumen-Ninja", "es": "Etraynze la Ninja de Flor Sombra", "fr": "Etraynze la Femme Ninja de la Fleur de l'Ombre", "it": "Etraynze la Ninja Fiore dell'Ombra", "pt": null, "ja": "<ruby>\u82b1<rt>\u304b</rt></ruby><ruby>\u7259<rt>\u3052</rt></ruby>\u30af\u30ce\u30a4\u30c1\u30fb\u30a8\u30c8\u30e9\u30f3\u30bc", "ja_romaji": "Kage Kunoichi Etoranze", "ko": "\ud654\uc544 \ucfe0\ub178\uc774\uce58 \uc5d0\ud2b8\ub791\uc81c", "ko_rr": null, "zh-TW": null, "zh-CN": null}, "requirement": {"en": "You have \"Etraynze the Shadow Flower Ninja\" in your Graveyard.", "de": null, "es": null, "fr": null, "it": null, "pt": null, "ja": "\u81ea\u5206\u306e\u5893\u5730\u306b\u300c\u82b1\u7259\u30af\u30ce\u30a4\u30c1\u30fb\u30a8\u30c8\u30e9\u30f3\u30bc\u300d\u304c\u3044\u308b\u5834\u5408\u306b\u767a\u52d5\u3067\u304d\u308b\u3002", "ko": "\uc790\uc2e0 \ubb18\uc9c0\uc5d0 \"\ud654\uc544 \ucfe0\ub178\uc774\uce58 \uc5d0\ud2b8\ub791\uc81c\"\uac00 \uc788\uc744 \uacbd\uc6b0\uc5d0 \ubc1c\ub3d9\ud560 \uc218 \uc788\ub2e4.", "zh-TW": null, "zh-CN": null}, "effect": {"en": null, "de": null, "es": null, "fr": null, "it": null, "pt": null, "ja": null, "ko": null, "zh-TW": null, "zh-CN": null}, "card_type": "Monster", "monster_type_line": "Plant / Effect", "attribute": "EARTH", "level": 7, "atk": 2300, "def": 1000, "series": ["Shadow Flower"], "images": [{"index": 1, "image": "EtraynzetheShadowFlowerNinja-RDSA03-JP-ScR.png"}], "sets": {"ja": [{"set_number": "RD/KP05-JP029", "set_name": "Deck Mod Pack: Dynamic Eternal Live!!", "rarities": ["Super Rare"]}, {"set_number": "RD/SA03-JP005", "set_name": "Secret Ace Pack Vol.3", "rarities": ["Secret Rare"]}], "ko": [{"set_number": "RD/KP05-KR029", "set_name": "Deck Mod Pack: Dynamic Eternal Live!!", "rarities": ["Super Rare"]}, {"set_number": "RD/EV05-KR003", "set_name": "Rush Duel Event Pack 2024 Vol.1", "rarities": ["Common", "Secret Rare"]}]}, "yugipedia_page_id": 714820}