{"konami_id": 19788, "name": {"en": "Shadow Flower Dance", "de": null, "es": null, "fr": null, "it": null, "pt": null, "ja": "<ruby>\u82b1<rt>\u304b</rt></ruby><ruby>\u7259<rt>\u3052</rt></ruby><ruby>\u862d<rt>\u3089\u3093</rt></ruby><ruby>\u821e<rt>\u3076</rt></ruby>", "ja_romaji": "Kageranbu", "ko": "\ud654\uc544\ub09c\ubb34", "ko_rr": null, "zh-TW": null, "zh-CN": null}, "requirement": {"en": "If you have a monster on your field, shuffle 3 Plant Type monsters from your Graveyard into the Deck.", "de": null, "es": null, "fr": null, "it": null, "pt": null, "ja": "\u81ea\u5206\u30d5\u30a3\u30fc\u30eb\u30c9\u306b\u30e2\u30f3\u30b9\u30bf\u30fc\u304c\u3044\u308b\u5834\u5408\u3001\u81ea\u5206\u306e\u5893\u5730\u306e\u30e2\u30f3\u30b9\u30bf\u30fc\uff08\u690d\u7269\u65cf\uff09\uff13\u4f53\u3092\u30c7\u30c3\u30ad\u306b\u623b\u3057\u3066\u767a\u52d5\u3067\u304d\u308b\u3002", "ko": "\uc790\uc2e0 \ud544\ub4dc\uc5d0 \ubaac\uc2a4\ud130\uac00 \uc788\uc744 \uacbd\uc6b0, \uc790\uc2e0 \ubb18\uc9c0\uc758 \ubaac\uc2a4\ud130(\uc2dd\ubb3c\uc871) 3\uc7a5\uc744 \ub371\uc73c\ub85c \ub418\ub3cc\ub9ac\uace0 \ubc1c\ub3d9\ud560 \uc218 \uc788\ub2e4.", "zh-TW": null, "zh-CN": null}, "effect": {"en": "Draw 1 card. Then, you can make up to 3 face-up non-Plant Type monsters on your opponent's field lose 300 ATK/DEF until the end of this turn.", "de": null, "es": null, "fr": null, "it": null, "pt": null, "ja": "\u81ea\u5206\u306f\uff11\u679a\u30c9\u30ed\u30fc\u3059\u308b\u3002\u305d\u306e\u5f8c\u3001\u76f8\u624b\u30d5\u30a3\u30fc\u30eb\u30c9\u306e\u8868\u5074\u8868\u793a\u30e2\u30f3\u30b9\u30bf\u30fc\uff08\u690d\u7269\u65cf\u4ee5\u5916\uff09\u3092\uff13\u4f53\u307e\u3067\u9078\u3093\u3067\u305d\u306e\u653b\u6483\u529b\u30fb\u5b88\u5099\u529b\u3092\u30bf\u30fc\u30f3\u7d42\u4e86\u6642\u307e\u3067\uff13\uff10\uff10\u30c0\u30a6\u30f3\u3067\u304d\u308b\u3002", "ko": "\uc790\uc2e0\uc740 1\uc7a5 \ub4dc\ub85c\uc6b0\ud55c\ub2e4. \uadf8 \ud6c4, \uc0c1\ub300 \ud544\ub4dc\uc758 \uc55e\uba74 \ud45c\uc2dc \ubaac\uc2a4\ud130(\uc2dd\ubb3c\uc871 \uc774\uc678)\ub97c 3\uc7a5\uae4c\uc9c0 \uace0\ub974\uace0 \uadf8 \uacf5\uaca9\ub825 / \uc218\ube44\ub825\uc744 \ud134 \uc885\ub8cc\uc2dc\uae4c\uc9c0 300 \ub0b4\ub9b4 \uc218 \uc788\ub2e4.", "zh-TW": null, "zh-CN": null}, "card_type": "Spell", "property": "Normal", "series": ["Shadow Flower"], "images": [{"index": 1, "image": "ShadowFlowerDance-RDHC01-JP-C.png"}], "sets": {"ja": [{"set_number": "RD/HC01-JP067", "set_name": "High-Grade Collection", "rarities": ["Common", "Secret Rare"]}], "ko": [{"set_number": "RD/HC01-KR062", "set_name": "High-Grade Collection", "rarities": ["Common", "Secret Rare"]}]}, "is_translation_unofficial": {"text": {"en": true}}, "yugipedia_page_id": 1034451}