{"konami_id": 7350, "password": 4923662, "name": {"en": "Chaos Burst", "de": "Chaosausbruch", "es": "Estallido del Caos", "fr": "Explosion Chaotique", "it": "Esplosione di Caos", "pt": "Explos\u00e3o do Caos", "ja": "\u30ab\u30aa\u30b9\u30fb\u30d0\u30fc\u30b9\u30c8", "ja_romaji": "Kaosu B\u0101suto", "ko": "\uce74\uc624\uc2a4 \ubc84\uc2a4\ud2b8", "ko_rr": null, "zh-TW": "\u6df7\u6c8c\u7206\u88c2", "zh-CN": "\u6df7\u6c8c\u7206\u88c2"}, "text": {"en": "When your opponent's monster declares an attack: Tribute 1 monster, then target the attacking monster; destroy that target, then inflict 1000 damage to your opponent.", "de": "Wenn ein Monster deines Gegners einen Angriff deklariert: Biete 1 Monster als Tribut an und w\u00e4hle dann das angreifende Monster; zerst\u00f6re das gew\u00e4hlte Ziel, dann f\u00fcge deinem Gegner 1000 Schaden zu.", "es": "Cuando un monstruo de tu adversario declara un ataque: Sacrifica 1 monstruo, y despu\u00e9s selecciona al monstruo atacante; destruye ese objetivo, y despu\u00e9s inflige 1000 puntos de da\u00f1o a tu adversario.", "fr": "Lorsqu'un monstre de votre adversaire d\u00e9clare une attaque : Sacrifiez 1 monstre, puis ciblez le monstre attaquant ; d\u00e9truisez la cible, puis infligez 1000 points de dommages \u00e0 votre adversaire.", "it": "Quando un mostro del tuo avversario dichiara un attacco: offri come Tributo 1 mostro, poi scegli come bersaglio il mostro attaccante; distruggi quel bersaglio, poi infliggi 1000 danni al tuo avversario.", "pt": "Quando um monstro do seu oponente declarar um ataque: ofere\u00e7a 1 monstro como Tributo e, depois, escolha o monstro atacante; destrua o alvo e, depois, cause 1000 de dano ao seu oponente.", "ja": "\u2460\uff1a\u76f8\u624b\u30e2\u30f3\u30b9\u30bf\u30fc\u306e\u653b\u6483\u5ba3\u8a00\u6642\u306b\u81ea\u5206\u30d5\u30a3\u30fc\u30eb\u30c9\u306e\u30e2\u30f3\u30b9\u30bf\u30fc\uff11\u4f53\u3092\u30ea\u30ea\u30fc\u30b9\u3057\u3001\u305d\u306e\u653b\u6483\u30e2\u30f3\u30b9\u30bf\u30fc\uff11\u4f53\u3092\u5bfe\u8c61\u3068\u3057\u3066\u767a\u52d5\u3067\u304d\u308b\u3002\u305d\u306e\u653b\u6483\u30e2\u30f3\u30b9\u30bf\u30fc\u3092\u7834\u58ca\u3059\u308b\u3002\u305d\u306e\u5f8c\u3001\u76f8\u624b\u306b\uff11\uff10\uff10\uff10\u30c0\u30e1\u30fc\u30b8\u3092\u4e0e\u3048\u308b\u3002", "ko": "\u2460: \uc0c1\ub300 \ubaac\uc2a4\ud130\uc758 \uacf5\uaca9 \uc120\uc5b8\uc2dc\uc5d0 \uc790\uc2e0 \ud544\ub4dc\uc758 \ubaac\uc2a4\ud130 1\uc7a5\uc744 \ub9b4\ub9ac\uc2a4\ud558\uace0, \uadf8 \uacf5\uaca9 \ubaac\uc2a4\ud130 1\uc7a5\uc744 \ub300\uc0c1\uc73c\ub85c \ud558\uc5ec \ubc1c\ub3d9\ud560 \uc218 \uc788\ub2e4. \uadf8 \uacf5\uaca9 \ubaac\uc2a4\ud130\ub97c \ud30c\uad34\ud55c\ub2e4. \uadf8 \ud6c4, \uc0c1\ub300\uc5d0\uac8c 1000 \ub370\ubbf8\uc9c0\ub97c \uc900\ub2e4.", "zh-TW": null, "zh-CN": "\u2460\uff1a\u5bf9\u65b9\u602a\u517d\u7684\u653b\u51fb\u5ba3\u8a00\u65f6\u628a\u81ea\u5df1\u573a\u4e0a1\u53ea\u602a\u517d\u89e3\u653e\uff0c\u4ee5\u90a31\u53ea\u653b\u51fb\u602a\u517d\u4e3a\u5bf9\u8c61\u624d\u80fd\u53d1\u52a8\u3002\u90a3\u53ea\u653b\u51fb\u602a\u517d\u7834\u574f\u3002\u90a3\u4e4b\u540e\uff0c\u7ed9\u4e0e\u5bf9\u65b91000\u4f24\u5bb3\u3002"}, "card_type": "Trap", "property": "Normal", "series": ["Chaos"], "images": [{"index": 1, "image": "ChaosBurst-YS16-EN-C-1E.png"}], "sets": {"en": [{"set_number": "GX04-EN003", "set_name": "Yu-Gi-Oh! GX Tag Force 2 promotional cards", "rarities": ["Super Rare"]}, {"set_number": "BP03-EN203", "set_name": "Battle Pack 3: Monster League", "rarities": ["Common", "Shatterfoil Rare"]}, {"set_number": "YS16-EN039", "set_name": "Starter Deck: Yuya", "rarities": ["Common"]}], "de": [{"set_number": "GX04-DE003", "set_name": "Yu-Gi-Oh! GX Tag Force 2 promotional cards", "rarities": ["Super Rare"]}, {"set_number": "BP03-DE203", "set_name": "Battle Pack 3: Monster League", "rarities": ["Common", "Shatterfoil Rare"]}, {"set_number": "YS16-DE039", "set_name": "Starter Deck: Yuya", "rarities": ["Common"]}], "es": [{"set_number": "GX04-SP003", "set_name": "Yu-Gi-Oh! GX Tag Force 2 promotional cards", "rarities": ["Super Rare"]}, {"set_number": "BP03-SP203", "set_name": "Battle Pack 3: Monster League", "rarities": ["Common", "Shatterfoil Rare"]}, {"set_number": "YS16-SP039", "set_name": "Starter Deck: Yuya", "rarities": ["Common"]}], "fr": [{"set_number": "GX04-FR003", "set_name": "Yu-Gi-Oh! GX Tag Force 2 promotional cards", "rarities": ["Super Rare"]}, {"set_number": "BP03-FR203", "set_name": "Battle Pack 3: Monster League", "rarities": ["Common", "Shatterfoil Rare"]}, {"set_number": "YS16-FR039", "set_name": "Starter Deck: Yuya", "rarities": ["Common"]}], "it": [{"set_number": "GX04-IT003", "set_name": "Yu-Gi-Oh! GX Tag Force 2 promotional cards", "rarities": ["Super Rare"]}, {"set_number": "BP03-IT203", "set_name": "Battle Pack 3: Monster League", "rarities": ["Common", "Shatterfoil Rare"]}, {"set_number": "YS16-IT039", "set_name": "Starter Deck: Yuya", "rarities": ["Common"]}], "pt": [{"set_number": "BP03-PT203", "set_name": "Battle Pack 3: Monster League", "rarities": ["Common", "Shatterfoil Rare"]}, {"set_number": "YS16-PT039", "set_name": "Starter Deck: Yuya", "rarities": ["Common"]}], "ja": [{"set_number": "GX04-JP003", "set_name": "Yu-Gi-Oh! GX Tag Force 2 promotional cards", "rarities": ["Ultra Rare"]}, {"set_number": "ST16-JP039", "set_name": "Starter Deck 2016", "rarities": ["Common"]}], "ko": [{"set_number": "ST16-KR039", "set_name": "Starter Deck 2016", "rarities": ["Common"]}]}, "limit_regulation": {"tcg": "Unlimited", "ocg": "Unlimited"}, "yugipedia_page_id": 510322, "master_duel_rarity": "R"}