{"konami_id": 9304, "password": 14677495, "name": {"en": "Tanngnjostr of the Nordic Beasts", "de": "Nordisches Ungeheuer Tanngnjostr", "es": "Tanngnjostr de las Bestias N\u00f3rdicas", "fr": "Tanngnj\u00f3str, B\u00eate Nordique", "it": "Tanngnjostr delle Bestie Nordic", "pt": "Tanngnjostr das Bestas N\u00f3rdicas", "ja": "<ruby>\u6975<rt>\u304d\u3087\u304f</rt></ruby><ruby>\u661f<rt>\u305b\u3044</rt></ruby><ruby>\u7363<rt>\u3058\u3085\u3046</rt></ruby>\u30bf\u30f3\u30b0\u30cb\u30e7\u30fc\u30b9\u30c8", "ja_romaji": "Kyokuseij\u016b Tanguny\u014dsuto", "ko": "\uadf9\uc131\uc218 \ud0d5\uadf8\ub1e8\uc2a4\ud2b8", "ko_rr": null, "zh-TW": "\u6975\u661f\u7378 \u5766\u683c\u55ac\u65af\u7279", "zh-CN": "\u6781\u661f\u517d\u00a0\u5766\u683c\u4e54\u65af\u7279"}, "text": {"en": "When a monster you control is destroyed by battle and sent to the GY: You can Special Summon this card from your hand. Once per turn, when this Defense Position card on the field is changed to face-up Attack Position: You can Special Summon 1 \"Nordic Beast\" monster from your Deck in Defense Position, except \"Tanngnjostr of the Nordic Beasts\".", "de": "Wenn ein Monster, das du kontrollierst, durch Kampf zerst\u00f6rt und auf den Friedhof gelegt wird: Du kannst diese Karte als Spezialbeschw\u00f6rung von deiner Hand beschw\u00f6ren. Einmal pro Spielzug, wenn diese Karte in Verteidigungsposition auf dem Spielfeld in die offene Angriffsposition ge\u00e4ndert wird: Du kannst 1 \u201eNordisches Ungeheuer\u201c-Monster als Spezialbeschw\u00f6rung von deinem Deck in die Verteidigungsposition beschw\u00f6ren, au\u00dfer \u201eNordisches Ungeheuer Tanngnjostr\u201c.", "es": "Cuando un monstruo que controlas es destruido en batalla y mandado al Cementerio: puedes Invocar esta carta de Modo Especial desde tu mano. Una vez por turno, cuando esta carta en Posici\u00f3n de Defensa en el Campo es cambiada a Posici\u00f3n de Ataque boca arriba: puedes Invocar de Modo Especial, desde tu Deck, 1 monstruo \"Bestia/s N\u00f3rdica/s\" en Posici\u00f3n de Defensa, excepto \"Tanngnjostr de las Bestias N\u00f3rdicas\".", "fr": "Lorsqu'un monstre que vous contr\u00f4lez est d\u00e9truit au combat et envoy\u00e9 au Cimeti\u00e8re : vous pouvez Invoquer Sp\u00e9cialement cette carte depuis votre main. Une fois par tour, lorsque cette carte en Position de D\u00e9fense sur le Terrain est chang\u00e9e en Position d'Attaque face recto : vous pouvez Invoquer Sp\u00e9cialement 1 monstre \"B\u00eate Nordique\" (\"Tanngnj\u00f3str, B\u00eate Nordique\" exclu) depuis votre Deck en Position de D\u00e9fense.", "it": "Quando un mostro che controlli viene distrutto in battaglia e mandato al Cimitero: puoi Evocare Specialmente questa carta dalla tua mano. Una volta per turno, quando questa carta in Posizione di Difesa sul Terreno viene messa scoperta in Posizione di Attacco: puoi Evocare Specialmente dal tuo Deck in Posizione di Difesa 1 mostro \"Bestia Nordic\", eccetto \"Tanngnjostr delle Bestie Nordic\".", "pt": "Quando um monstro que voc\u00ea controla for destru\u00eddo em batalha e enviado para o Cemit\u00e9rio: voc\u00ea pode Invocar este card por Invoca\u00e7\u00e3o-Especial da sua m\u00e3o. Uma vez por turno, quando este card em Posi\u00e7\u00e3o de Defesa no campo for colocado com a face para cima em Posi\u00e7\u00e3o de Ataque: voc\u00ea pode Invocar por Invoca\u00e7\u00e3o-Especial 1 monstro \"Besta(s) N\u00f3rdica(s)\" do seu Deck em Posi\u00e7\u00e3o de Defesa, exceto \"Tanngnjostr das Bestas N\u00f3rdicas\".", "ja": "\u81ea\u5206\u30d5\u30a3\u30fc\u30eb\u30c9\u4e0a\u306b\u5b58\u5728\u3059\u308b\u30e2\u30f3\u30b9\u30bf\u30fc\u304c\u6226\u95d8\u306b\u3088\u3063\u3066\u7834\u58ca\u3055\u308c\u5893\u5730\u3078\u9001\u3089\u308c\u305f\u6642\u3001\u3053\u306e\u30ab\u30fc\u30c9\u3092\u624b\u672d\u304b\u3089\u7279\u6b8a\u53ec\u559a\u3059\u308b\u4e8b\u304c\u3067\u304d\u308b\u3002\uff11\u30bf\u30fc\u30f3\u306b\uff11\u5ea6\u3001\u30d5\u30a3\u30fc\u30eb\u30c9\u4e0a\u306b\u5b88\u5099\u8868\u793a\u3067\u5b58\u5728\u3059\u308b\u3053\u306e\u30ab\u30fc\u30c9\u304c\u8868\u5074\u653b\u6483\u8868\u793a\u306b\u306a\u3063\u305f\u6642\u3001\u81ea\u5206\u306e\u30c7\u30c3\u30ad\u304b\u3089\u300c\u6975\u661f\u7363\u30bf\u30f3\u30b0\u30cb\u30e7\u30fc\u30b9\u30c8\u300d\u4ee5\u5916\u306e\u300c\u6975\u661f\u7363\u300d\u3068\u540d\u306e\u3064\u3044\u305f\u30e2\u30f3\u30b9\u30bf\u30fc\uff11\u4f53\u3092\u8868\u5074\u5b88\u5099\u8868\u793a\u3067\u7279\u6b8a\u53ec\u559a\u3059\u308b\u4e8b\u304c\u3067\u304d\u308b\u3002", "ko": "\uc790\uc2e0 \ud544\ub4dc \uc704\uc5d0 \uc874\uc7ac\ud558\ub294 \ubaac\uc2a4\ud130\uac00 \uc804\ud22c\uc5d0 \uc758\ud574\uc11c \ud30c\uad34\ub418\uc5b4 \ubb18\uc9c0\ub85c \ubcf4\ub0b4\uc84c\uc744 \ub54c, \uc774 \uce74\ub4dc\ub97c \ud328\uc5d0\uc11c \ud2b9\uc218 \uc18c\ud658\ud560 \uc218 \uc788\ub2e4. 1\ud134\uc5d0 1\ubc88, \ud544\ub4dc \uc704\uc5d0 \uc218\ube44 \ud45c\uc2dc\ub85c \uc874\uc7ac\ud558\ub294 \uc774 \uce74\ub4dc\uac00 \uc55e\uba74 \uacf5\uaca9 \ud45c\uc2dc\ub85c \ub418\uc5c8\uc744 \ub54c, \uc790\uc2e0\uc758 \ub371\uc5d0\uc11c \"\uadf9\uc131\uc218 \ud0d5\uadf8\ub1e8\uc2a4\ud2b8\" \uc774\uc678\uc758 \"\uadf9\uc131\uc218\"\ub77c\ub294 \uc774\ub984\uc774 \ubd99\uc740 \ubaac\uc2a4\ud130 1\uc7a5\uc744 \uc55e\uba74 \uc218\ube44 \ud45c\uc2dc\ub85c \ud2b9\uc218 \uc18c\ud658\ud560 \uc218 \uc788\ub2e4.", "zh-TW": null, "zh-CN": "\u81ea\u5df1\u573a\u4e0a\u5b58\u5728\u7684\u602a\u517d\u88ab\u6218\u6597\u7834\u574f\u9001\u53bb\u5893\u5730\u65f6\uff0c\u8fd9\u5f20\u5361\u53ef\u4ee5\u4ece\u624b\u5361\u7279\u6b8a\u53ec\u5524\u30021\u56de\u54081\u6b21\uff0c\u573a\u4e0a\u5b88\u5907\u8868\u793a\u5b58\u5728\u7684\u8fd9\u5f20\u5361\u53d8\u6210\u8868\u4fa7\u653b\u51fb\u8868\u793a\u65f6\uff0c\u53ef\u4ee5\u4ece\u81ea\u5df1\u5361\u7ec4\u628a\u300c\u6781\u661f\u517d \u5766\u683c\u4e54\u65af\u7279\u300d\u4ee5\u5916\u76841\u53ea\u540d\u5b57\u5e26\u6709\u300c\u6781\u661f\u517d\u300d\u7684\u602a\u517d\u8868\u4fa7\u5b88\u5907\u8868\u793a\u7279\u6b8a\u53ec\u5524\u3002"}, "card_type": "Monster", "monster_type_line": "Beast / Effect", "attribute": "EARTH", "level": 3, "atk": 800, "def": 1100, "series": ["Nordic", "Nordic Beast"], "images": [{"index": 1, "image": "TanngnjostroftheNordicBeasts-OP18-EN-C-UE.png"}], "sets": {"en": [{"set_number": "STOR-EN013", "set_name": "Storm of Ragnarok", "rarities": ["Rare"]}, {"set_number": "LC5D-EN180", "set_name": "Legendary Collection 5D's Mega Pack", "rarities": ["Secret Rare"]}, {"set_number": "LEHD-ENB02", "set_name": "Legendary Hero Decks", "rarities": ["Common"]}, {"set_number": "OP18-EN014", "set_name": "OTS Tournament Pack 18", "rarities": ["Common"]}], "de": [{"set_number": "STOR-DE013", "set_name": "Storm of Ragnarok", "rarities": ["Rare"]}, {"set_number": "LC5D-DE180", "set_name": "Legendary Collection 5D's Mega Pack", "rarities": ["Secret Rare"]}, {"set_number": "LEHD-DEB02", "set_name": "Legendary Hero Decks", "rarities": ["Common"]}, {"set_number": "OP18-DE014", "set_name": "OTS Tournament Pack 18", "rarities": ["Common"]}], "es": [{"set_number": "STOR-SP013", "set_name": "Storm of Ragnarok", "rarities": ["Rare"]}, {"set_number": "LC5D-SP180", "set_name": "Legendary Collection 5D's Mega Pack", "rarities": ["Secret Rare"]}, {"set_number": "LEHD-SPB02", "set_name": "Legendary Hero Decks", "rarities": ["Common"]}, {"set_number": "OP18-SP014", "set_name": "OTS Tournament Pack 18", "rarities": ["Common"]}], "fr": [{"set_number": "STOR-FR013", "set_name": "Storm of Ragnarok", "rarities": ["Rare"]}, {"set_number": "LC5D-FR180", "set_name": "Legendary Collection 5D's Mega Pack", "rarities": ["Secret Rare"]}, {"set_number": "LEHD-FRB02", "set_name": "Legendary Hero Decks", "rarities": ["Common"]}, {"set_number": "OP18-FR014", "set_name": "OTS Tournament Pack 18", "rarities": ["Common"]}], "it": [{"set_number": "STOR-IT013", "set_name": "Storm of Ragnarok", "rarities": ["Rare"]}, {"set_number": "LC5D-IT180", "set_name": "Legendary Collection 5D's Mega Pack", "rarities": ["Secret Rare"]}, {"set_number": "LEHD-ITB02", "set_name": "Legendary Hero Decks", "rarities": ["Common"]}, {"set_number": "OP18-IT014", "set_name": "OTS Tournament Pack 18", "rarities": ["Common"]}], "pt": [{"set_number": "LC5D-PT180", "set_name": "Legendary Collection 5D's Mega Pack", "rarities": ["Secret Rare"]}, {"set_number": "LEHD-PTB02", "set_name": "Legendary Hero Decks", "rarities": ["Common"]}, {"set_number": "OP18-PT014", "set_name": "OTS Tournament Pack 18", "rarities": ["Common"]}], "ja": [{"set_number": "STOR-JP013", "set_name": "Storm of Ragnarok", "rarities": ["Rare"]}], "ko": [{"set_number": "STOR-KR013", "set_name": "Storm of Ragnarok", "rarities": ["Rare"]}]}, "limit_regulation": {"tcg": "Unlimited", "ocg": "Unlimited"}, "yugipedia_page_id": 135556, "master_duel_rarity": "N"}