{"konami_id": 6058, "password": 39719977, "name": {"en": "Delta Attacker", "de": "Delta-Angreifer", "es": "Atacante Delta", "fr": "Agresseur Delta", "it": "Attaccante Delta", "pt": "Atacante Delta", "ja": "\u30c7\u30eb\u30bf\u30fb\u30a2\u30bf\u30c3\u30ab\u30fc", "ja_romaji": "Deruta Atakk\u0101", "ko": "\ub378\ud0c0 \uc5b4\ud0dc\ucee4", "ko_rr": null, "zh-TW": "\u4e09\u89d2\u653b\u52e2", "zh-CN": "\u4e09\u874e\u8054\u76df"}, "text": {"en": "You can only activate this card while there are 3 Normal Monsters of the same name (except Tokens) on your side of the field. The 3 Normal Monsters of the same name can attack your opponent's Life Points directly during the turn this card is activated.", "de": "Du kannst diese Karte nur aktivieren, wenn sich 3 normale Monster des gleichen Namens (ausgenommen Monsterspielmarken) auf deiner Spielfeldseite befinden. Die 3 normalen Monster mit gleichem Namen k\u00f6nnen die Life Points deines Gegners in diesem Spielzug direkt angreifen.", "es": "S\u00f3lo puedes activar esta carta cuando hay 3 Monstruos Normales del mismo nombre (excepto fichas) en tu Campo. Los 3 Monstruos Normales del mismo nombre pueden atacar los Life Points de tu adversario directamente durante este turno.", "fr": "Vous ne pouvez activer cette carte que s'il y a 3 Monstres Normaux portant le m\u00eame nom (except\u00e9 les jetons) sur votre Terrain. Les 3 Monstres Normaux portant le m\u00eame nom peuvent attaquer directement les Life Points de votre adversaire durant ce tour-ci.", "it": "Puoi attivare questa carta solo quando ci sono 3 Mostri Normali con lo stesso nome (eccetto i Segna-Mostro) scoperti sul tuo Terreno. I 3 Mostri Normali con lo stesso nome possono attaccare direttamente i Life Points del tuo avversario durante questo turno.", "pt": "Voc\u00ea pode activar este card apenas quando estiverem 3 Monstros Normais com o mesmo nome (exceto Fichas) no seu Campo. Os 3 Monstros Normais com o mesmo nome podem atacar diretamente os Life Points do seu advers\u00e1rio este turno.", "ja": "\u81ea\u5206\u30d5\u30a3\u30fc\u30eb\u30c9\u4e0a\u306b\u540c\u540d\u901a\u5e38\u30e2\u30f3\u30b9\u30bf\u30fc\uff08\u30c8\u30fc\u30af\u30f3\u3092\u9664\u304f\uff09\u304c\uff13\u4f53\u5b58\u5728\u3059\u308b\u6642\u306b\u767a\u52d5\u3059\u308b\u4e8b\u304c\u3067\u304d\u308b\u3002\u767a\u52d5\u30bf\u30fc\u30f3\u306e\u307f\u3001\uff13\u4f53\u306e\u540c\u540d\u901a\u5e38\u30e2\u30f3\u30b9\u30bf\u30fc\u306f\u76f8\u624b\u30d7\u30ec\u30a4\u30e4\u30fc\u306b\u76f4\u63a5\u653b\u6483\u3059\u308b\u4e8b\u304c\u3067\u304d\u308b\u3002", "ko": "\uc790\uc2e0 \ud544\ub4dc \uc704\uc5d0 \uac19\uc740 \uc774\ub984\uc758 \uc77c\ubc18 \ubaac\uc2a4\ud130(\ud1a0\ud070 \uc774\uc678)\uac00 3\uc7a5 \uc874\uc7ac\ud560 \ub54c \ubc1c\ub3d9\ud560 \uc218 \uc788\ub2e4. \ubc1c\ub3d9 \ud134\uc5d0\ub9cc, 3\uc7a5\uc758 \uac19\uc740 \uc774\ub984\uc758 \uc77c\ubc18 \ubaac\uc2a4\ud130\ub294 \uc0c1\ub300 \ud50c\ub808\uc774\uc5b4\uc5d0\uac8c \uc9c1\uc811 \uacf5\uaca9\uc744 \ud560 \uc218 \uc788\ub2e4.", "zh-TW": null, "zh-CN": "\u81ea\u5df1\u573a\u4e0a\u6709\u540c\u540d\u901a\u5e38\u602a\u517d\uff08\u9664\u884d\u751f\u7269\u5916\uff093\u53ea\u5b58\u5728\u65f6\u624d\u80fd\u53d1\u52a8\u3002\u53ea\u5728\u53d1\u52a8\u56de\u5408\uff0c3\u53ea\u540c\u540d\u901a\u5e38\u602a\u517d\u53ef\u4ee5\u76f4\u63a5\u653b\u51fb\u5bf9\u65b9\u73a9\u5bb6\u3002"}, "card_type": "Spell", "property": "Normal", "images": [{"index": 1, "image": "DeltaAttacker-DR2-EN-C-UE.png"}], "sets": {"en": [{"set_number": "DR2-EN209", "set_name": "Dark Revelation Volume 2", "rarities": ["Common"]}, {"set_number": "AST-096", "set_name": "Ancient Sanctuary", "rarities": ["Common"]}], "de": [{"set_number": "AST-DE096", "set_name": "Ancient Sanctuary", "rarities": ["Common"]}, {"set_number": "DR2-DE209", "set_name": "Dark Revelation Volume 2", "rarities": ["Common"]}], "fr": [{"set_number": "AST-FR096", "set_name": "Ancient Sanctuary", "rarities": ["Common"]}, {"set_number": "DR2-FR209", "set_name": "Dark Revelation Volume 2", "rarities": ["Common"]}], "it": [{"set_number": "AST-IT096", "set_name": "Ancient Sanctuary", "rarities": ["Common"]}, {"set_number": "DR2-IT209", "set_name": "Dark Revelation Volume 2", "rarities": ["Common"]}], "pt": [{"set_number": "AST-PT096", "set_name": "Ancient Sanctuary", "rarities": ["Common"]}], "ja": [{"set_number": "309-041", "set_name": "Pharaoh's Inheritance", "rarities": ["Common"]}, {"set_number": "EE2-JP209", "set_name": "Expert Edition Volume.2", "rarities": ["Common"]}], "ko": [{"set_number": "AST-KR096", "set_name": "Ancient Sanctuary", "rarities": ["Common"]}, {"set_number": "HGP2-KR209", "set_name": "Expert Edition Volume.2", "rarities": ["Common"]}]}, "limit_regulation": {"tcg": "Unlimited", "ocg": "Unlimited"}, "yugipedia_page_id": 12058, "master_duel_rarity": "N"}