{"konami_id": 10340, "password": 61344030, "name": {"en": "Starliege Paladynamo", "de": "Sternenvasall Paladynamo", "es": "Se\u00f1orestelar Palad\u00ednamo", "fr": "Paladynamo Seigneur des \u00c9toiles", "it": "Paladinamo Stellavassallo", "pt": "Palad\u00ednamo Gal\u00e1ctico", "ja": "<ruby>\u8f1d<rt>\u304d</rt></ruby><ruby>\u5149<rt>\u3053\u3046</rt></ruby><ruby>\u5b50<rt>\u3057</rt></ruby>\u30d1\u30e9\u30c7\u30a3\u30aa\u30b9", "ja_romaji": "Kik\u014dshi Paradiosu", "ko": "\ud718\uad11\uc790 \ud30c\ub77c\ub514\uc624\uc2a4", "ko_rr": null, "zh-TW": "\u8f1d\u5149\u516c\u5b50\u5e15\u62c9\u8fea\u5967\u65af", "zh-CN": "\u8f89\u5149\u516c\u5b50\u5e15\u62c9\u8fea\u5965\u65af"}, "text": {"en": "2 Level 4 LIGHT monsters\nOnce per turn: You can detach 2 Xyz Materials from this card, then target 1 face-up monster your opponent controls; change its ATK to 0, and if you do, it has its effects negated. If this card you control is destroyed by an opponent's card (by battle or card effect) and sent to your GY: Draw 1 card.", "de": "2 LICHT Monster der Stufe 4\nEinmal pro Spielzug: Du kannst 2 Xyz-Material von dieser Karte abh\u00e4ngen und dann 1 offenes Monster w\u00e4hlen, das dein Gegner kontrolliert; \u00e4ndere seine ATK zu 0 und falls du dies tust, bleiben seine Effekte annulliert. Falls diese Karte, die du kontrollierst, durch eine Karte deines Gegners (durch Kampf oder einen Karteneffekt) zerst\u00f6rt und auf deinen Friedhof gelegt wird: Ziehe 1 Karte.", "es": "2 monstruos de LUZ de Nivel 4\nUna vez por turno: puedes desacoplar de esta carta 2 Materiales Xyz, y despu\u00e9s seleccionar 1 monstruo boca arriba que controle tu adversario; cambia su ATK a 0 y, si lo haces, \u00e9ste ve sus efectos negados. Si esta carta que controlas es destruida por una carta de tu adversario (ya sea en batalla o por un efecto de carta) y mandada a tu Cementerio: roba 1 carta.", "fr": "2 monstres LUMI\u00c8RE de Niveau 4\nUne fois par tour : vous pouvez d\u00e9tacher 2 Mat\u00e9riels Xyz de cette carte, puis ciblez 1 monstre face recto contr\u00f4l\u00e9 par votre adversaire ; changez son ATK \u00e0 0, et si vous le faites, il a ses effets annul\u00e9s. Si cette carte que vous contr\u00f4lez est d\u00e9truite par une carte de votre adversaire (au combat ou par un effet de carte) et envoy\u00e9e \u00e0 votre Cimeti\u00e8re : piochez 1 carte.", "it": "2 mostri LUCE di Livello 4\nUna volta per turno: puoi staccare 2 Materiali Xyz da questa carta, poi scegliere come bersaglio 1 mostro scoperto controllato dal tuo avversario; cambia il suo ATK a 0 e, se lo fai, i suoi effetti si annullano. Se questa carta che controlli viene distrutta da una carta dell'avversario (in battaglia o dall'effetto di una carta) e mandata al tuo Cimitero: pesca 1 carta.", "pt": "2 monstros de LUZ de N\u00edvel 4\nUma vez por turno: voc\u00ea pode desassociar 2 Mat\u00e9rias Xyz deste card e, depois, escolher 1 monstro com a face para cima que seu oponente controla; mude o ATK dele para 0 e, se isso acontecer, ele tem seus efeitos negados. Se este card que voc\u00ea controla for destru\u00eddo por um card do seu oponente (em batalha ou por um efeito de card) e enviado para o seu Cemit\u00e9rio: compre 1 card.", "ja": "\u5149\u5c5e\u6027\u30ec\u30d9\u30eb\uff14\u30e2\u30f3\u30b9\u30bf\u30fc\u00d7\uff12\n\u2460\uff1a\uff11\u30bf\u30fc\u30f3\u306b\uff11\u5ea6\u3001\u3053\u306e\u30ab\u30fc\u30c9\u306e\uff38\u7d20\u6750\u3092\uff12\u3064\u53d6\u308a\u9664\u304d\u3001\u76f8\u624b\u30d5\u30a3\u30fc\u30eb\u30c9\u306e\u8868\u5074\u8868\u793a\u30e2\u30f3\u30b9\u30bf\u30fc\uff11\u4f53\u3092\u5bfe\u8c61\u3068\u3057\u3066\u767a\u52d5\u3067\u304d\u308b\u3002\u305d\u306e\u30e2\u30f3\u30b9\u30bf\u30fc\u306e\u653b\u6483\u529b\u3092\uff10\u306b\u3057\u3001\u305d\u306e\u52b9\u679c\u3092\u7121\u52b9\u306b\u3059\u308b\u3002\u2461\uff1a\u30d5\u30a3\u30fc\u30eb\u30c9\u306e\u3053\u306e\u30ab\u30fc\u30c9\u304c\u76f8\u624b\u306b\u3088\u3063\u3066\u7834\u58ca\u3055\u308c\u5893\u5730\u3078\u9001\u3089\u308c\u305f\u5834\u5408\u306b\u767a\u52d5\u3059\u308b\u3002\u81ea\u5206\u306f\u30c7\u30c3\u30ad\u304b\u3089\uff11\u679a\u30c9\u30ed\u30fc\u3059\u308b\u3002", "ko": "\ube5b \uc18d\uc131 \ub808\ubca8 4 \ubaac\uc2a4\ud130 \u00d7 2\n\u2460: 1\ud134\uc5d0 1\ubc88, \uc774 \uce74\ub4dc\uc758 \uc5d1\uc2dc\uc988 \uc18c\uc7ac\ub97c 2\uac1c \uc81c\uac70\ud558\uace0, \uc0c1\ub300 \ud544\ub4dc\uc758 \uc55e\uba74 \ud45c\uc2dc \ubaac\uc2a4\ud130 1\uc7a5\uc744 \ub300\uc0c1\uc73c\ub85c \ud558\uc5ec \ubc1c\ub3d9\ud560 \uc218 \uc788\ub2e4. \uadf8 \ubaac\uc2a4\ud130\uc758 \uacf5\uaca9\ub825\uc744 0 \uc73c\ub85c \ud558\uace0, \uadf8 \ud6a8\uacfc\ub97c \ubb34\ud6a8\ub85c \ud55c\ub2e4. \u2461: \ud544\ub4dc\uc758 \uc774 \uce74\ub4dc\uac00 \uc0c1\ub300\uc5d0 \uc758\ud574\uc11c \ud30c\uad34\ub418\uc5b4 \ubb18\uc9c0\ub85c \ubcf4\ub0b4\uc84c\uc744 \uacbd\uc6b0\uc5d0 \ubc1c\ub3d9\ud55c\ub2e4. \uc790\uc2e0\uc740 \ub371\uc5d0\uc11c 1\uc7a5 \ub4dc\ub85c\uc6b0\ud55c\ub2e4.", "zh-TW": null, "zh-CN": "\u5149\u5c5e\u6027\u7b49\u7ea74\u602a\u517d\u00d72\n\u2460\uff1a1\u56de\u54081\u6b21\uff0c\u53bb\u9664\u6b64\u5361\u76842\u4e2a\u8d85\u91cf\u7d20\u6750\uff0c\u53ef\u4ee5\u5bf9\u624b\u573a\u4e0a\u76841\u53ea\u8868\u4fa7\u8868\u793a\u7684\u602a\u517d\u4e3a\u5bf9\u8c61\u53d1\u52a8\u3002\u5c06\u8be5\u602a\u517d\u7684\u653b\u51fb\u529b\u6539\u62100\uff0c\u4f7f\u5176\u6548\u679c\u65e0\u6548\u3002\u2461\uff1a\u5728\u573a\u4e0a\u7684\u6b64\u5361\u88ab\u5bf9\u624b\u7834\u574f\u5e76\u9001\u81f3\u5893\u5730\u7684\u60c5\u51b5\u4e0b\u53d1\u52a8\u3002\u81ea\u5df1\u4ece\u724c\u7ec4\u4e2d\u62bd1\u5f20\u3002"}, "card_type": "Monster", "monster_type_line": "Warrior / Xyz / Effect", "attribute": "LIGHT", "rank": 4, "atk": 2000, "def": 1000, "materials": "2 Level 4 LIGHT monsters", "series": ["Starliege"], "images": [{"index": 1, "image": "StarliegePaladynamo-RA04-EN-PlScR-1E.png"}], "sets": {"en": [{"set_number": "ZTIN-EN014", "set_name": "Zexal Collection Tin", "rarities": ["Ultra Rare"]}, {"set_number": "DPDG-EN041", "set_name": "Duelist Pack: Dimensional Guardians", "rarities": ["Rare"]}, {"set_number": "RA04-EN193", "set_name": "Quarter Century Stampede", "rarities": ["Platinum Secret Rare", "Quarter Century Secret Rare"]}], "de": [{"set_number": "ZTIN-DE014", "set_name": "Zexal Collection Tin", "rarities": ["Ultra Rare"]}, {"set_number": "DPDG-DE041", "set_name": "Duelist Pack: Dimensional Guardians", "rarities": ["Rare"]}, {"set_number": "RA04-DE193", "set_name": "Quarter Century Stampede", "rarities": ["Platinum Secret Rare", "Quarter Century Secret Rare"]}], "es": [{"set_number": "ZTIN-SP014", "set_name": "Zexal Collection Tin", "rarities": ["Ultra Rare"]}, {"set_number": "DPDG-SP041", "set_name": "Duelist Pack: Dimensional Guardians", "rarities": ["Rare"]}, {"set_number": "RA04-SP193", "set_name": "Quarter Century Stampede", "rarities": ["Platinum Secret Rare", "Quarter Century Secret Rare"]}], "fr": [{"set_number": "ZTIN-FR014", "set_name": "Zexal Collection Tin", "rarities": ["Ultra Rare"]}, {"set_number": "DPDG-FR041", "set_name": "Duelist Pack: Dimensional Guardians", "rarities": ["Rare"]}, {"set_number": "RA04-FR193", "set_name": "Quarter Century Stampede", "rarities": ["Platinum Secret Rare", "Quarter Century Secret Rare"]}], "it": [{"set_number": "ZTIN-IT014", "set_name": "Zexal Collection Tin", "rarities": ["Ultra Rare"]}, {"set_number": "DPDG-IT041", "set_name": "Duelist Pack: Dimensional Guardians", "rarities": ["Rare"]}, {"set_number": "RA04-IT193", "set_name": "Quarter Century Stampede", "rarities": ["Platinum Secret Rare", "Quarter Century Secret Rare"]}], "pt": [{"set_number": "ZTIN-PT014", "set_name": "Zexal Collection Tin", "rarities": ["Ultra Rare"]}, {"set_number": "DPDG-PT041", "set_name": "Duelist Pack: Dimensional Guardians", "rarities": ["Rare"]}, {"set_number": "RA04-PT193", "set_name": "Quarter Century Stampede", "rarities": ["Platinum Secret Rare", "Quarter Century Secret Rare"]}], "ja": [{"set_number": "DP13-JP022", "set_name": "Duelist Pack: Kite", "rarities": ["Ultra Rare"]}, {"set_number": "AT14-JP001", "set_name": "Advanced Tournament Pack 2016 Vol.2", "rarities": ["Normal Parallel Rare"]}], "ko": [{"set_number": "DP13-KR022", "set_name": "Duelist Pack: Kite", "rarities": ["Ultra Rare"]}, {"set_number": "AE09-KR020", "set_name": "Advanced Event Pack 2016 Vol.1", "rarities": ["Common"]}], "zh-CN": [{"set_number": "SD26-SCP08", "set_name": "Structure Deck: Blitzkrieg of the Mechlight Dragons Deck Enhancement Pack", "rarities": ["Super Rare"]}, {"set_number": "SCTP-SC045", "set_name": "Entry Pack Volume 3", "rarities": ["Common"]}]}, "limit_regulation": {"tcg": "Unlimited", "ocg": "Unlimited"}, "yugipedia_page_id": 235488, "master_duel_rarity": "SR"}