{"konami_id": 11827, "password": 83629030, "name": {"en": "Toon Cyber Dragon", "de": "Toon-Cyber Drache", "es": "Ciber Drag\u00f3n Toon", "fr": "Cyber Dragon Toon", "it": "Cyber Drago Toon", "pt": "Drag\u00e3o Cibern\u00e9tico Toon", "ja": "\u30c8\u30a5\u30fc\u30f3\u30fb\u30b5\u30a4\u30d0\u30fc\u30fb\u30c9\u30e9\u30b4\u30f3", "ja_romaji": "T\u016bn Saib\u0101 Doragon", "ko": "\ud230 \uc0ac\uc774\ubc84 \ub4dc\ub798\uace4", "ko_rr": null, "zh-TW": "\u5361\u901a\u96fb\u5b50\u9f8d", "zh-CN": "\u5361\u901a\u7535\u5b50\u9f99"}, "text": {"en": "If your opponent controls a monster and you control no monsters, you can Special Summon this card (from your hand). Cannot attack the turn it is Summoned. While you control \"Toon World\" and your opponent controls no Toon monsters, this card can attack your opponent directly.", "de": "Falls dein Gegner ein Monster kontrolliert und du keine Monster kontrollierst, kannst du diese Karte als Spezialbeschw\u00f6rung (von deiner Hand) beschw\u00f6ren. Diese Karte kann nicht in dem Spielzug angreifen, in dem sie beschworen wurde. Solange du \u201eToon-Welt\u201c kontrollierst und dein Gegner keine Toon-Monster kontrolliert, kann diese Karte deinen Gegner direkt angreifen.", "es": "Si tu adversario controla un monstruo y t\u00fa no controlas ninguno, puedes Invocar esta carta de Modo Especial (desde tu mano). No puede atacar en el turno en el que es Invocado. Mientras controles \"Mundo Toon\" y tu adversario no controle monstruos Toon, esta carta puede atacar a tu adversario directamente.", "fr": "Si votre adversaire contr\u00f4le un monstre et que vous n'en contr\u00f4lez aucun, vous pouvez Invoquer Sp\u00e9cialement cette carte (depuis votre main). Ne peut pas attaquer le tour o\u00f9 elle est Invoqu\u00e9e. Tant que vous contr\u00f4lez \"Monde des Toons\" et que votre adversaire ne contr\u00f4le aucun monstre Toon, cette carte peut attaquer directement votre adversaire.", "it": "Se il tuo avversario controlla un mostro e tu non controlli nessun mostro, puoi Evocare Specialmente questa carta (dalla tua mano). Non pu\u00f2 attaccare nel turno in cui viene Evocato. Mentre tu controlli \"Mondo Toon\" e il tuo avversario non controlla nessun mostro Toon, questa carta pu\u00f2 attaccare il tuo avversario direttamente.", "pt": "Se seu oponente controlar um monstro e voc\u00ea n\u00e3o controlar nenhum monstro, voc\u00ea pode Invocar este card por Invoca\u00e7\u00e3o-Especial (da sua m\u00e3o). N\u00e3o pode atacar no turno em que for Invocado. Enquanto voc\u00ea controlar \"Mundo Toon\" e seu oponente n\u00e3o controlar nenhum monstro Toon, este card pode atacar diretamente seu oponente.", "ja": "\u2460\uff1a\u76f8\u624b\u30d5\u30a3\u30fc\u30eb\u30c9\u306b\u30e2\u30f3\u30b9\u30bf\u30fc\u304c\u5b58\u5728\u3057\u3001\u81ea\u5206\u30d5\u30a3\u30fc\u30eb\u30c9\u306b\u30e2\u30f3\u30b9\u30bf\u30fc\u304c\u5b58\u5728\u3057\u306a\u3044\u5834\u5408\u3001\u3053\u306e\u30ab\u30fc\u30c9\u306f\u624b\u672d\u304b\u3089\u7279\u6b8a\u53ec\u559a\u3067\u304d\u308b\u3002\u2461\uff1a\u3053\u306e\u30ab\u30fc\u30c9\u306f\u53ec\u559a\u30fb\u53cd\u8ee2\u53ec\u559a\u30fb\u7279\u6b8a\u53ec\u559a\u3057\u305f\u30bf\u30fc\u30f3\u306b\u306f\u653b\u6483\u3067\u304d\u306a\u3044\u3002\u2462\uff1a\u81ea\u5206\u30d5\u30a3\u30fc\u30eb\u30c9\u306b\u300c\u30c8\u30a5\u30fc\u30f3\u30fb\u30ef\u30fc\u30eb\u30c9\u300d\u304c\u5b58\u5728\u3057\u3001\u76f8\u624b\u30d5\u30a3\u30fc\u30eb\u30c9\u306b\u30c8\u30a5\u30fc\u30f3\u30e2\u30f3\u30b9\u30bf\u30fc\u304c\u5b58\u5728\u3057\u306a\u3044\u5834\u5408\u3001\u3053\u306e\u30ab\u30fc\u30c9\u306f\u76f4\u63a5\u653b\u6483\u3067\u304d\u308b\u3002", "ko": "\u2460: \uc0c1\ub300 \ud544\ub4dc\uc5d0 \ubaac\uc2a4\ud130\uac00 \uc874\uc7ac\ud558\uace0, \uc790\uc2e0 \ud544\ub4dc\uc5d0 \ubaac\uc2a4\ud130\uac00 \uc874\uc7ac\ud558\uc9c0 \uc54a\uc744 \uacbd\uc6b0, \uc774 \uce74\ub4dc\ub294 \ud328\uc5d0\uc11c \ud2b9\uc218 \uc18c\ud658\ud560 \uc218 \uc788\ub2e4. \u2461: \uc774 \uce74\ub4dc\ub294 \uc77c\ubc18 \uc18c\ud658 / \ubc18\uc804 \uc18c\ud658 / \ud2b9\uc218 \uc18c\ud658\ud55c \ud134\uc5d0\ub294 \uacf5\uaca9\ud560 \uc218 \uc5c6\ub2e4. \u2462: \uc790\uc2e0 \ud544\ub4dc\uc5d0 \"\ud230 \uc6d4\ub4dc\"\uac00 \uc874\uc7ac\ud558\uace0, \uc0c1\ub300 \ud544\ub4dc\uc5d0 \ud230 \ubaac\uc2a4\ud130\uac00 \uc874\uc7ac\ud558\uc9c0 \uc54a\uc744 \uacbd\uc6b0, \uc774 \uce74\ub4dc\ub294 \uc9c1\uc811 \uacf5\uaca9\ud560 \uc218 \uc788\ub2e4.", "zh-TW": "\u2460\uff1a\u5728\u5c0d\u65b9\u5834\u4e0a\u5b58\u5728\u602a\u7378\uff0c\u6211\u65b9\u5834\u4e0a\u4e0d\u5b58\u5728\u602a\u7378\u7684\u72c0\u6cc1\u4e0b\uff0c\u53ef\u5f9e\u624b\u724c\u7279\u6b8a\u53ec\u559a\u6b64\u5361\u3002\u2461\uff1a\u6b64\u5361\u5728\u53ec\u559a\u30fb\u53cd\u8f49\u53ec\u559a\u30fb\u7279\u6b8a\u53ec\u559a\u7684\u56de\u5408\u7121\u6cd5\u653b\u64ca\u3002\u2462\uff1a\u5728\u6211\u65b9\u5834\u4e0a\u5b58\u5728\u300c\u5361\u901a\u4e16\u754c\u300d\uff0c\u5c0d\u65b9\u5834\u4e0a\u4e0d\u5b58\u5728\u5361\u901a\u602a\u7378\u7684\u72c0\u6cc1\u4e0b\uff0c\u6b64\u5361\u53ef\u76f4\u63a5\u653b\u64ca\u3002", "zh-CN": "\u2460\uff1a\u5bf9\u624b\u573a\u4e0a\u5b58\u5728\u6709\u602a\u517d\uff0c\u4e14\u6211\u65b9\u573a\u4e0a\u4e0d\u5b58\u5728\u6709\u602a\u517d\u7684\u573a\u5408\uff0c\u6b64\u5361\u53ef\u4ece\u624b\u724c\u7279\u6b8a\u53ec\u5524\u3002\u2461\uff1a\u6b64\u5361\u5728\u53ec\u5524\u3001\u53cd\u8f6c\u53ec\u5524\u3001\u7279\u6b8a\u53ec\u5524\u56de\u5408\u4e0d\u53ef\u653b\u51fb\u3002\u2462\uff1a\u6211\u65b9\u573a\u4e0a\u5b58\u5728\u6709\u201c\u5361\u901a\u4e16\u754c\u201d\uff0c\u4e14\u5bf9\u624b\u573a\u4e0a\u4e0d\u5b58\u5728\u6709\u5361\u901a\u602a\u517d\u7684\u573a\u5408\uff0c\u6b64\u5361\u53ef\u76f4\u63a5\u653b\u51fb\u3002"}, "card_type": "Monster", "monster_type_line": "Machine / Toon / Effect", "attribute": "LIGHT", "level": 5, "atk": 2100, "def": 1600, "series": ["Toon", "Cyber", "Cyber Dragon"], "images": [{"index": 1, "image": "ToonCyberDragon-LDS1-EN-C-1E.png"}], "sets": {"en": [{"set_number": "CORE-EN043", "set_name": "Clash of Rebellions", "rarities": ["Rare"]}, {"set_number": "MP16-EN074", "set_name": "2016 Mega-Tin Mega Pack", "rarities": ["Rare"]}, {"set_number": "LDS1-EN062", "set_name": "Legendary Duelists: Season 1", "rarities": ["Common"]}], "de": [{"set_number": "CORE-DE043", "set_name": "Clash of Rebellions", "rarities": ["Rare"]}, {"set_number": "MP16-DE074", "set_name": "2016 Mega-Tin Mega Pack", "rarities": ["Rare"]}, {"set_number": "LDS1-DE062", "set_name": "Legendary Duelists: Season 1", "rarities": ["Common"]}], "fr": [{"set_number": "CORE-FR043", "set_name": "Clash of Rebellions", "rarities": ["Rare"]}, {"set_number": "MP16-FR074", "set_name": "2016 Mega-Tin Mega Pack", "rarities": ["Rare"]}, {"set_number": "LDS1-FR062", "set_name": "Legendary Duelists: Season 1", "rarities": ["Common"]}], "it": [{"set_number": "CORE-IT043", "set_name": "Clash of Rebellions", "rarities": ["Rare"]}, {"set_number": "MP16-IT074", "set_name": "2016 Mega-Tin Mega Pack", "rarities": ["Rare"]}, {"set_number": "LDS1-IT062", "set_name": "Legendary Duelists: Season 1", "rarities": ["Common"]}], "pt": [{"set_number": "CORE-PT043", "set_name": "Clash of Rebellions", "rarities": ["Rare"]}, {"set_number": "MP16-PT074", "set_name": "2016 Mega-Tin Mega Pack", "rarities": ["Rare"]}, {"set_number": "LDS1-PT062", "set_name": "Legendary Duelists: Season 1", "rarities": ["Common"]}], "ja": [{"set_number": "CORE-JP043", "set_name": "Clash of Rebellions", "rarities": ["Rare"]}], "ko": [{"set_number": "CORE-KR043", "set_name": "Clash of Rebellions", "rarities": ["Rare"]}]}, "limit_regulation": {"tcg": "Unlimited", "ocg": "Unlimited"}, "yugipedia_page_id": 354273, "master_duel_rarity": "R"}