{"konami_id": null, "password": null, "name": {"en": "Magmacho Dragon", "de": null, "es": null, "fr": null, "it": null, "pt": null, "ja": "\u30de\u30b0\u30de\u30c3\u30c1\u30e7\u30fb\u30c9\u30e9\u30b4\u30f3", "ja_romaji": "Magumaccho Doragon", "ko": null, "ko_rr": null, "zh-TW": null, "zh-CN": null}, "text": {"en": "You can banish up to 3 FIRE monsters from your GY; this card gains 400 ATK for each, until the end of this turn. If a face-up FIRE monster(s) you control is destroyed by card effect while this card is in your GY: You can Special Summon this card (but banish it when it leaves the field), then draw 1 card. You can only use each effect of \"Magmacho Dragon\" once per turn.", "de": null, "es": null, "fr": null, "it": null, "pt": null, "ja": null, "ko": null, "zh-TW": null, "zh-CN": null}, "card_type": "Monster", "monster_type_line": "Pyro / Effect", "attribute": "FIRE", "level": 8, "atk": 1800, "def": 2200, "images": [{"index": 1, "image": "MagmachoDragon-PHNI-JP-OP.png"}], "sets": {"ja": [{"set_number": "PHNI-JP025", "set_name": "Phantom Nightmare", "rarities": null}]}, "limit_regulation": {"tcg": "Not yet released", "ocg": "Not yet released"}, "is_translation_unofficial": {"name": {"en": true}, "text": {"en": true}}, "yugipedia_page_id": 1018876, "fake_password": [101203025]}