{"konami_id": null, "password": null, "name": {"en": "Sarv Sarga", "de": null, "es": null, "fr": null, "it": null, "pt": null, "ja": "<ruby>\u65b0\u4e16\u5efb<rt>\u30b7\u30e3\u30eb\u30f4\u30fb\u30b5\u30eb\u30ac</rt></ruby>", "ja_romaji": "Sharuvu Saruga", "ko": null, "ko_rr": null, "zh-TW": null, "zh-CN": null}, "text": {"en": "If \"Visas Starfrost\" is on the field: Target 1 Effect Monster on the field; shuffle that target into the Deck, and if you do, during the End Phase of this turn, its owner can add 1 monster from their Deck to their hand with a different Type and a lower Level than the shuffled monster's Level/Rank/Link Rating. If a \"Veda\" monster(s) is Special Summoned while this card is in your GY (except during the Damage Step): You can add this card to your hand. You can only use each effect of \"Sarv Sarga\" once per turn.", "de": null, "es": null, "fr": null, "it": null, "pt": null, "ja": null, "ko": null, "zh-TW": null, "zh-CN": null}, "card_type": "Trap", "property": "Normal", "images": [{"index": 1, "image": "SarvSarga-AGOV-JP-C.png"}], "sets": {"ja": [{"set_number": "AGOV-JP072", "set_name": "Age of Overlord", "rarities": null}]}, "limit_regulation": {"tcg": "Not yet released", "ocg": "Not yet released"}, "is_translation_unofficial": {"name": {"en": true}, "text": {"en": true}}, "yugipedia_page_id": 978656, "fake_password": [101202072]}